dev_lxc/__init__.py
dev_lxc/cmd.py
dev_lxc-0.4.2.dist-info/LICENSE
dev_lxc-0.4.2.dist-info/METADATA
dev_lxc-0.4.2.dist-info/WHEEL
dev_lxc-0.4.2.dist-info/entry_points.txt
dev_lxc-0.4.2.dist-info/RECORD
