Metadata-Version: 2.3
Name: dev-lxc
Version: 0.4.2
Summary: A small wrapper for creating LXD system containers for development purposes.
License: MIT
Author: Mitch Burton
Author-email: mitch@mitchellburton.ca
Maintainer: Mitch Burton
Maintainer-email: mitch@mitchellburton.ca
Requires-Python: >=3.10
Classifier: Development Status :: 4 - Beta
Classifier: Environment :: Console
Classifier: Intended Audience :: Developers
Classifier: License :: OSI Approved :: MIT License
Classifier: Operating System :: POSIX :: Linux
Classifier: Programming Language :: Python :: 3
Classifier: Programming Language :: Python :: 3.10
Classifier: Programming Language :: Python :: 3.11
Classifier: Programming Language :: Python :: 3.12
Classifier: Programming Language :: Python :: 3.13
Classifier: Topic :: Software Development
Requires-Dist: PyYAML (>=6.0.1,<7.0.0)
Project-URL: Repository, https://github.com/Perfect5th/dev-lxc
